MANIFEST.in
setup.py
gretry/README.md
gretry/__init__.py
gretry/error_jump.py
gretry/gretry.py
gretry.egg-info/PKG-INFO
gretry.egg-info/SOURCES.txt
gretry.egg-info/dependency_links.txt
gretry.egg-info/top_level.txt