Metadata-Version: 2.1
Name: gretry
Version: 2.0.6
Summary: 一个错误重试装饰器
Home-page: https://github.com/Leviathangk/gretry
Author: 郭一会儿
Author-email: 1015295213@qq.com
License: MIT Licence
Keywords: retry,retrying
Platform: any
